# Python Bytecode: Advanced Professional & Technical Insights

## **Table of Contents**
- [Understanding Python Bytecode](#understanding-python-bytecode)
- [1. How Bytecode Works Internally](#1-how-bytecode-works-internally)
- [2. Difference Between .pyc and .pyo](#2-difference-between-pyc-and-pyo)
- [3. Why Bytecode Can't Be Understood by the CPU](#3-why-bytecode-cant-be-understood-by-the-cpu)
- [4. How the Python Virtual Machine (PVM) Executes Bytecode](#4-how-the-python-virtual-machine-pvm-executes-bytecode)
- [5. Examples: Bytecode at Different Levels](#5-examples-bytecode-at-different-levels)
  - [Basic Example: Bytecode for a Simple Python Program](#basic-example-bytecode-for-a-simple-python-program)
  - [Medium Example: Bytecode for a Loop](#medium-example-bytecode-for-a-loop)
  - [Advanced Example: Bytecode for a Function](#advanced-example-bytecode-for-a-function)
  - [Expert-Level Example: Bytecode for Recursion](#expert-level-example-bytecode-for-recursion)
- [6. Inputs & Outputs of the Python Virtual Machine](#6-inputs--outputs-of-the-python-virtual-machine)
- [7. Key Takeaways for Software Engineers](#7-key-takeaways-for-software-engineers)
- [Final Thoughts](#final-thoughts)

---

## **Understanding Python Bytecode**
Python **bytecode** is an intermediate representation of Python source code that is executed by the **Python Virtual Machine (PVM)**. It is not machine code but a **low-level instruction set** optimized for execution by the PVM.

---

## **1. How Bytecode Works Internally**
- Python **compiles** source code into **bytecode** (`.pyc` or `.pyo` files).
- The **Python Virtual Machine (PVM)** executes the bytecode **line by line**.
- Bytecode **is platform-independent** and optimized for execution by the PVM.

---

## **2. Difference Between .pyc and .pyo**
| **File Type**  | **Purpose** |
|---------------|------------|
| `.pyc` (Python Compiled) | Stores **compiled bytecode** for faster execution. |
| `.pyo` (Python Optimized) | Stores **optimized bytecode** with optimizations (Python 2 only, removed in Python 3.5). |

---

## **3. Why Bytecode Can't Be Understood by the CPU**
- The **CPU only understands machine code (binary 0s and 1s)**.
- Bytecode is **optimized for PVM execution**, not for direct CPU processing.
- Bytecode must be **interpreted by PVM**, which translates it into machine instructions dynamically.

---

## **4. How the Python Virtual Machine (PVM) Executes Bytecode**
| **Step** | **Process** |
|----------|------------|
| **1. Load Bytecode** | The `.pyc` file is **loaded into memory**. |
| **2. Fetch Instruction** | The PVM **fetches** the next bytecode instruction. |
| **3. Decode & Execute** | The instruction is **decoded** and **executed** by the PVM. |
| **4. Repeat Until Completion** | The PVM continues execution **until all instructions are processed**. |

---

## **5. Examples: Bytecode at Different Levels**

### **Basic Example: Bytecode for a Simple Python Program**
```python
print("Hello, World!")
```
**Bytecode Output:**
```plaintext
  1           0 LOAD_NAME                0 (print)
              2 LOAD_CONST               1 ('Hello, World!')
              4 CALL_FUNCTION            1
              6 POP_TOP
              8 RETURN_VALUE
```

### **Medium Example: Bytecode for a Loop**
```python
for i in range(3):
    print(i)
```
**Bytecode Output:**
```plaintext
  1           0 LOAD_NAME                0 (range)
              2 LOAD_CONST               1 (3)
              4 CALL_FUNCTION            1
              6 GET_ITER
        >>    8 FOR_ITER                 4 (to 18)
             10 STORE_NAME               1 (i)
             12 LOAD_NAME                2 (print)
             14 LOAD_NAME                1 (i)
             16 CALL_FUNCTION            1
             18 POP_TOP
             20 JUMP_ABSOLUTE            8
             22 RETURN_VALUE
```

### **Advanced Example: Bytecode for a Function**
```python
def square(n):
    return n * n

print(square(4))
```
**Bytecode Output:**
```plaintext
  1           0 LOAD_CONST               1 (<code object square>)
              2 LOAD_CONST               2 ('square')
              4 MAKE_FUNCTION            0
              6 STORE_NAME               0 (square)
  4           8 LOAD_NAME                1 (print)
             10 LOAD_NAME                0 (square)
             12 LOAD_CONST               3 (4)
             14 CALL_FUNCTION            1
             16 CALL_FUNCTION            1
             18 POP_TOP
             20 RETURN_VALUE
```

### **Expert-Level Example: Bytecode for Recursion**
```python
def factorial(n):
    if n == 1:
        return 1
    return n * factorial(n - 1)

print(factorial(5))
```
**Bytecode Output:**
```plaintext
  1           0 LOAD_CONST               1 (<code object factorial>)
              2 LOAD_CONST               2 ('factorial')
              4 MAKE_FUNCTION            0
              6 STORE_NAME               0 (factorial)
  7           8 LOAD_NAME                1 (print)
             10 LOAD_NAME                0 (factorial)
             12 LOAD_CONST               3 (5)
             14 CALL_FUNCTION            1
             16 CALL_FUNCTION            1
             18 POP_TOP
             20 RETURN_VALUE
```

---

## **6. Inputs & Outputs of the Python Virtual Machine**
| **Component** | **Input** | **Output** |
|--------------|---------|---------|
| **Python Compiler** | `.py` source file | `.pyc` bytecode file |
| **Python Virtual Machine (PVM)** | `.pyc` bytecode | Machine code for CPU execution |
| **CPU Execution** | Machine code | Final program output |

---

## **7. Key Takeaways for Software Engineers**
- **Python does not execute `.py` files directly**; it first compiles them to bytecode.
- **Bytecode is stored in `.pyc` files** in the `__pycache__` directory.
- **The Python Virtual Machine (PVM)** interprets bytecode and executes it **line by line**.
- **Compiled bytecode speeds up execution** by avoiding recompilation on each run.

---

## **Final Thoughts**
Understanding Python bytecode helps software engineers optimize performance, debug more effectively, and gain deeper insights into Python's execution model.
